AUTHORS.rst
LICENSE
MANIFEST.in
README.txt
setup.py
parcel/__init__.py
parcel/cache.py
parcel/distro.py
parcel/helpers.py
parcel/probes.py
parcel/revisions.py
parcel/tools.py
parcel/versions.py
parcel.egg-info/PKG-INFO
parcel.egg-info/SOURCES.txt
parcel.egg-info/dependency_links.txt
parcel.egg-info/requires.txt
parcel.egg-info/top_level.txt
parcel/defaults/__init__.py
parcel/defaults/centos.py
parcel/defaults/debian.py
parcel/deploy/__init__.py
parcel/deploy/deploy.py
parcel/deploy/uwsgi.py