Metadata-Version: 1.1
Name: parcel
Version: 0.2.1
Summary: Python Webapp Deployment Made Easier.
Home-page: https://bitbucket.org/andrewmacgregor/parcel
Author: Crispin Wellington
Author-email: retrogradeorbit@gmail.com
License: Copyright (c) 2012 Crispin Wellington.
